scratchgpt/__init__.py
scratchgpt/config.py
scratchgpt/infer.py
scratchgpt/metering.py
scratchgpt/model_io.py
scratchgpt/train.py
scratchgpt/core/__init__.py
scratchgpt/core/types.py
scratchgpt/data/__init__.py
scratchgpt/data/datasource.py
scratchgpt/data/hf_datasource.py
scratchgpt/model/model.py
scratchgpt/tokenizer/base_tokenizer.py
scratchgpt/tokenizer/char_tokenizer.py
scratchgpt/tokenizer/hf_tokenizer.py
scratchgpt/training/tokenize_utils.py
scratchgpt/training/trainer.py
scratchgpt-0.5.1.dist-info/METADATA
scratchgpt-0.5.1.dist-info/WHEEL
scratchgpt-0.5.1.dist-info/entry_points.txt
scratchgpt-0.5.1.dist-info/licenses/LICENSE
scratchgpt-0.5.1.dist-info/RECORD
