Metadata-Version: 2.4
Name: scratchgpt
Version: 0.5.1
Summary: A small-scale transformer-based language model implemented from scratch in Python.
Project-URL: Homepage, https://github.com/LabStrangeLoop/scratchgpt
Project-URL: Repository, https://github.com/LabStrangeLoop/scratchgpt
Author-email: Aleksandr Yeganov <ayeganov@gmail.com>, Dario Cazzani <dariocazzani@gmail.com>
License: MIT License
License-File: LICENSE
Keywords: deep-learning,gpt,language-model,pytorch,tokenizer,transformer
Classifier: Development Status :: 3 - Alpha
Classifier: Intended Audience :: Developers
Classifier: Intended Audience :: Science/Research
Classifier: License :: OSI Approved :: MIT License
Classifier: Operating System :: OS Independent
Classifier: Programming Language :: Python :: 3
Classifier: Programming Language :: Python :: 3.12
Classifier: Topic :: Scientific/Engineering :: Artificial Intelligence
Requires-Python: >=3.12
Requires-Dist: datasets>=4.0.0
Requires-Dist: numpy>=2.3.2
Requires-Dist: ptflops>=0.7.5
Requires-Dist: pydantic-settings>=2.10.1
Requires-Dist: pydantic-yaml>=1.6.0
Requires-Dist: torch>=2.8.0
Requires-Dist: tqdm>=4.67.1
Requires-Dist: types-tqdm>=4.67.0.20250809
Provides-Extra: hf-tokenizers
Requires-Dist: huggingface-hub>=0.34.4; extra == 'hf-tokenizers'
Requires-Dist: tokenizers>=0.19.0; extra == 'hf-tokenizers'
